scriptorium/__init__.py
scriptorium/__main__.py
scriptorium/_version.py
scriptorium/config.py
scriptorium/install.py
scriptorium/papers.py
scriptorium/templates.py
scriptorium/data/gitignore
scriptorium-2.7.3.dist-info/DESCRIPTION.rst
scriptorium-2.7.3.dist-info/METADATA
scriptorium-2.7.3.dist-info/RECORD
scriptorium-2.7.3.dist-info/WHEEL
scriptorium-2.7.3.dist-info/entry_points.txt
scriptorium-2.7.3.dist-info/metadata.json
scriptorium-2.7.3.dist-info/top_level.txt
