Metadata-Version: 2.0
Name: scriptorium
Version: 2.7.3
Summary: Multimarkdown and LaTeX framework for academic papers.
Home-page: https://github.com/jasedit/scriptorium
Author: Jason Ziglar
Author-email: jasedit@gmail.com
License: MIT
Platform: UNKNOWN
Classifier: Development Status :: 4 - Beta
Classifier: Intended Audience :: Developers
Classifier: Topic :: Text Processing :: Markup
Classifier: Topic :: Text Processing :: Filters
Classifier: Topic :: Software Development :: Libraries :: Python Modules
Classifier: License :: OSI Approved :: MIT License
Classifier: Programming Language :: Python :: 2
Classifier: Programming Language :: Python :: 3
Requires-Dist: argcomplete
Requires-Dist: pymmd (>=0.3)
Requires-Dist: pyyaml
